pypdfops/__init__.py
pypdfops/pypdfops.py
pypdfops-0.0.3.dist-info/LICENCE
pypdfops-0.0.3.dist-info/METADATA
pypdfops-0.0.3.dist-info/WHEEL
pypdfops-0.0.3.dist-info/top_level.txt
pypdfops-0.0.3.dist-info/RECORD
