Metadata-Version: 2.1
Name: pypdfops
Version: 0.0.3
Summary: A utility library for pdf manupulation
Home-page: https://github.com/Nitesh-13/PyPDFOps
Author: Nitesh (limelight)
Author-email: <ritu10mali@gmail.com>
Project-URL: Bug Reports, https://github.com/Nitesh-13/PyPDFOps/issues
Project-URL: Source, https://github.com/Nitesh-13/PyPDFOps
Keywords: python,pdf,compress,pdf to pptx,pdf to doc,merge pdf,split pdf,pdf to image
Classifier: Development Status :: 1 - Planning
Classifier: Intended Audience :: Developers
Classifier: Programming Language :: Python :: 3
Classifier: Operating System :: Unix
Classifier: Operating System :: MacOS :: MacOS X
Classifier: Operating System :: Microsoft :: Windows
License-File: LICENCE
Requires-Dist: pdf2docx
Requires-Dist: pdf2image
Requires-Dist: pdf2pptx
Requires-Dist: PDFNetPython3
Requires-Dist: PyMuPDF
Requires-Dist: PyPDF2
